cngn_manager/AESCrypto.py
cngn_manager/CryptoWallet.py
cngn_manager/Ed25519Crypto.py
cngn_manager/WalletManager.py
cngn_manager/__init__.py
cngn_manager/__version__.py
cngn_manager/constants.py
cngn_manager/main.py
cngn_manager-1.0.3.dist-info/LICENSE
cngn_manager-1.0.3.dist-info/METADATA
cngn_manager-1.0.3.dist-info/WHEEL
cngn_manager-1.0.3.dist-info/top_level.txt
cngn_manager-1.0.3.dist-info/RECORD
