Metadata-Version: 2.2
Name: cngn_manager
Version: 1.0.3
Summary: Python HTTP for Humans.
Home-page: https://docs.cngn.co
Author: Emmanuel Onyo
Author-email: emmanuel.onyo@withconvexity.com
License: MIT License
Project-URL: Documentation, https://docs.cngn.co
Project-URL: Source, https://github.com/wrappedcbdc/cngn-pyhon-library.git
Requires-Python: >=3.8
License-File: LICENSE
Requires-Dist: requests
Requires-Dist: cryptography==43.0.1
Requires-Dist: pynacl==1.5.0
Requires-Dist: mnemonic==0.20
Requires-Dist: bip32utils==0.3.post4
Requires-Dist: hashlib
Requires-Dist: tronpy
Requires-Dist: stellar-sdk==11.1.0
Dynamic: author
Dynamic: author-email
Dynamic: description
Dynamic: description-content-type
Dynamic: home-page
Dynamic: license
Dynamic: project-url
Dynamic: requires-dist
Dynamic: requires-python
Dynamic: summary
